mailwand/__init__.py
mailwand/mailwand.py
mailwand-1.0.0.dist-info/LICENSE
mailwand-1.0.0.dist-info/METADATA
mailwand-1.0.0.dist-info/WHEEL
mailwand-1.0.0.dist-info/top_level.txt
mailwand-1.0.0.dist-info/RECORD
