Metadata-Version: 2.1
Name: mailwand
Version: 1.0.0
Summary: easy to send email
Home-page: https://github.com/we684123/MailWand
Author: we684123
Author-email: we684123@gmail.com
License: MIT
Keywords: mail,email,embed,image,mailsender,mailwand
Platform: any
Requires-Python: >=3.5
Requires-Dist: get-filename (>=1.0)
Requires-Dist: coloredlogs (>=14.0)
Requires-Dist: humanfriendly (>=7.1)
